visorRobot/__init__.py
visorRobot/visor.py
visorRobot03-0.0.1.dist-info/METADATA
visorRobot03-0.0.1.dist-info/WHEEL
visorRobot03-0.0.1.dist-info/top_level.txt
visorRobot03-0.0.1.dist-info/RECORD
